climateserv/__init__.py
climateserv/api.py
climateserv/request_utilities.py
climateserv-1.0.8.dist-info/LICENSE
climateserv-1.0.8.dist-info/METADATA
climateserv-1.0.8.dist-info/WHEEL
climateserv-1.0.8.dist-info/top_level.txt
climateserv-1.0.8.dist-info/RECORD
