Metadata-Version: 2.1
Name: climateserv
Version: 1.0.8
Summary: This is a package to access the ClimateSERV API](https://climateserv.servirglobal.net/) 
Home-page: https://github.com/servir/ClimateSERVpy
Author: Billy Ashmall
Author-email: billy.ashmall@nasa.gov
Classifier: Programming Language :: Python :: 3
Classifier: License :: OSI Approved :: MIT License
Classifier: Operating System :: OS Independent
Requires-Python: >=3.8
License-File: LICENSE
Requires-Dist: requests
